LICENSE
MANIFEST.in
README.md
pyproject.toml
setup.py
src/batchtsocmd/__init__.py
src/batchtsocmd/main.py
src/batchtsocmd.egg-info/PKG-INFO
src/batchtsocmd.egg-info/SOURCES.txt
src/batchtsocmd.egg-info/dependency_links.txt
src/batchtsocmd.egg-info/entry_points.txt
src/batchtsocmd.egg-info/requires.txt
src/batchtsocmd.egg-info/top_level.txt
tests/test_concatenated_datasets.py
tests/test_dataset_operations.py
tests/test_db2cmd.py