Metadata-Version: 2.4
Name: batchtsocmd
Version: 0.1.9
Summary: Run TSO commands via IKJEFT1B
Author: Mike Fulton
License: Apache-2.0
Project-URL: Homepage, https://github.com/MikeFultonDev/batchtsocmd
Project-URL: Repository, https://github.com/MikeFultonDev/batchtsocmd
Project-URL: Issues, https://github.com/MikeFultonDev/batchtsocmd/issues
Keywords: zos,tso,mainframe,ebcdic,ikjeft1b
Classifier: Development Status :: 3 - Alpha
Classifier: Environment :: Console
Classifier: Intended Audience :: Developers
Classifier: Intended Audience :: System Administrators
Classifier: License :: OSI Approved :: Apache Software License
Classifier: Operating System :: Other OS
Classifier: Programming Language :: Python :: 3
Classifier: Programming Language :: Python :: 3.8
Classifier: Programming Language :: Python :: 3.9
Classifier: Programming Language :: Python :: 3.10
Classifier: Programming Language :: Python :: 3.11
Classifier: Programming Language :: Python :: 3.12
Classifier: Programming Language :: Python :: 3.13
Classifier: Programming Language :: Python :: 3.14
Classifier: Topic :: Software Development :: Libraries :: Python Modules
Classifier: Topic :: System :: Systems Administration
Requires-Python: >=3.8
License-File: LICENSE
Requires-Dist: zoautil-py
Requires-Dist: zos-ccsid-converter>=0.1.8
Requires-Dist: packaging>=20.0
Provides-Extra: dev
Requires-Dist: pytest>=7.0.0; extra == "dev"
Requires-Dist: build>=0.10.0; extra == "dev"
Requires-Dist: twine<4.0.0,>=3.0.0; extra == "dev"
Requires-Dist: readme-renderer<35.0,>=21.0; extra == "dev"
Provides-Extra: test
Requires-Dist: pytest>=7.0.0; extra == "test"
Dynamic: license-file
